{
    "content": [
        {
            "left": [
                "D1",
                "",
                "香港-科伦坡-尼甘布"
            ],
            "right": [
                {
                    "flight": {
                        "duration": "5h25min",
                        "from": "香港",
                        "to_time": "23:15",
                        "begin_time": "",
                        "to": "科伦坡",
                        "begin_place": "香港赤鱲角国际机场",
                        "from_time": "20:15"
                    }
                },
                {
                    "sight": {
                        "name": "Goldi Sands Hotel"
                    }
                }
            ],
            "middle": [
                {
                    "icon": "flight",
                    "text": "香港-科伦坡-尼甘布"
                },
                {
                    "icon": "hotel",
                    "text": "Goldi Sands Hotel"
                }
            ]
        },
        {
            "left": [
                "D2",
                "",
                "尼甘布-锡吉里耶"
            ],
            "middle": [
                {
                    "icon": "sight",
                    "text": "Pinnawala Elephant Orphanage"
                },
                {
                    "icon": "sight",
                    "text": "Sigiriya Rock Fortress"
                },
				{
                    "icon": "activity",
                    "text": "School Visiting"
                },
                {
                    "icon": "hotel",
                    "text": "Elephas Resort"
                }
            ],
            "right": [
                {
                    "sight": {
                        "name": "Pinnawala Elephant Orphanage"
                    }
                },
                {
                    "sight": {
                        "name": "Sigiriya Rock Fortress"
                    }
                },
				{
                    "sight": {
                        "name": "School Visiting"
                    }
                },
                {
                    "sight": {
                        "name": "Elephas Resort"
                    }
                }
            ]
        },
        {
            "left": [
                "D3",
                "",
                "锡吉里耶-亭可马里"
            ],
            "middle": [
                {
                    "icon": "sight",
                    "text": "Polonnaruwa Ancient City"
                },
                {
                    "icon": "hotel",
                    "text": "Pigeon Island Resort"
                }
            ],
            "right": [
                {
                    "sight": {
                        "name": "Polonnaruwa Ancient City"
                    }
                },
                {
                    "sight": {
                        "name": "Pigeon Island Resort"
                    }
                }
            ]
        },
        {
            "left": [
                "D4",
                "",
                "亭可马里"
            ],
            "middle": [
                {
                    "icon": "sight",
                    "text": "Fort Frederick"
                },
                {
                    "icon": "sight",
                    "text": "Swami Rock"
                },
                {
                    "icon": "sight",
                    "text": "Koneswaram Kovil"
                },
                {
                    "icon": "hotel",
                    "text": "Pigeon Island Resort"
                }
            ],
            "right": [
                {
                    "sight": {
                        "name": "Fort Frederick"
                    }
                },
                {
                    "sight": {
                        "name": "Fort Frederick"
                    }
                },
                {
                    "sight": {
                        "name": "Koneswaram Kovil"
                    }
                },
                {
                    "sight": {
                        "name": "Pigeon Island Resort"
                    }
                }
            ]
        },
        {
            "left": [
                "D5",
                "",
                "亭可马里-康提"
            ],
            "middle": [
                {
                    "icon": "sight",
                    "text": "Sri Dalada Maligawa"
                },
                {
                    "icon": "sight",
                    "text": "Kandy Lake"
                },
                {
                    "icon": "activity",
                    "text": "Gamini Gems"
                },
                {
                    "icon": "hotel",
                    "text": "Earls Regency Hotel"
                }
            ],
            "right": [
                {
                    "sight": {
                        "name": "Sri Dalada Maligawa"
                    }
                },
                {
                    "sight": {
                        "name": "Kandy Lake"
                    }
                },
                {
                    "sight": {
                        "name": "Gamini Gemsvalue"
                    }
                },
                {
                    "sight": {
                        "name": "Earls Regency Hotel"
                    }
                }
            ]
        },
        {
            "left": [
                "D6",
                "",
                "康提-科伦坡"
            ],
            "middle": [
                {
                    "icon": "sight",
                    "text": "Independence Square"
                },
                {
                    "icon": "sight",
                    "text": "Old Muncipal Council"
                },
                {
                    "icon": "sight",
                    "text": "Gangaramaya Temple"
                },
                {
                    "icon": "sight",
                    "text": "Galle Face Green"
                },
                {
                    "icon": "hotel",
                    "text": "Galle Face Hotel"
                }
            ],
            "right": [
                {
                    "sight": {
                        "name": "Independence Square"
                    }
                },
                {
                    "sight": {
                        "name": "Old Muncipal Council"
                    }
                },
                {
                    "sight": {
                        "name": "Gangaramaya Temple"
                    }
                },
                {
                    "sight": {
                        "name": "Galle Face Green"
                    }
                },
                {
                    "sight": {
                        "name": "Galle Face Hotel"
                    }
                }
            ]
        },
        {
            "left": [
                "D7",
                "",
                "科伦坡-香港"
            ],
            "right": [
                {
                    "flight": {
                        "duration": "7h20min",
                        "from": "科伦坡",
                        "to_time": "17:10",
                        "begin_time": "曼谷经停",
                        "to": "香港",
                        "begin_place": "香港赤鱲角国际机场",
                        "from_time": "07:20"
                    }
                }
            ],
            "middle": [
                {
                    "icon": "flight",
                    "text": "科伦坡-香港"
                }
            ]
        }
    ]
}
